qtex
