Metadata-Version: 2.1
Name: qtex
Version: 0.0.6
Summary: Quant Trading
Home-page: 
Author: Andrew Hu
Author-email: AndrewWeiHu@gmail.com
Platform: any
